tests/__init__.py
tests/test_client.py
tests/test_config.py
tests/test_upwork.py
tests/routers/__init__.py
tests/routers/test_graphql.py
upwork/__init__.py
upwork/client.py
upwork/config.py
upwork/upwork.py
upwork/routers/__init__.py
upwork/routers/auth.py
upwork/routers/graphql.py
upwork/routers/messages.py
upwork/routers/metadata.py
upwork/routers/payments.py
upwork/routers/snapshots.py
upwork/routers/workdays.py
upwork/routers/workdiary.py
upwork/routers/activities/__init__.py
upwork/routers/activities/engagement.py
upwork/routers/activities/team.py
upwork/routers/freelancers/__init__.py
upwork/routers/freelancers/profile.py
upwork/routers/freelancers/search.py
upwork/routers/hr/__init__.py
upwork/routers/hr/contracts.py
upwork/routers/hr/engagements.py
upwork/routers/hr/interviews.py
upwork/routers/hr/jobs.py
upwork/routers/hr/milestones.py
upwork/routers/hr/roles.py
upwork/routers/hr/submissions.py
upwork/routers/hr/clients/__init__.py
upwork/routers/hr/clients/applications.py
upwork/routers/hr/clients/offers.py
upwork/routers/hr/freelancers/__init__.py
upwork/routers/hr/freelancers/applications.py
upwork/routers/hr/freelancers/offers.py
upwork/routers/jobs/__init__.py
upwork/routers/jobs/profile.py
upwork/routers/jobs/search.py
upwork/routers/organization/__init__.py
upwork/routers/organization/companies.py
upwork/routers/organization/teams.py
upwork/routers/organization/users.py
upwork/routers/reports/__init__.py
upwork/routers/reports/time.py
upwork/routers/reports/finance/__init__.py
upwork/routers/reports/finance/accounts.py
upwork/routers/reports/finance/billings.py
upwork/routers/reports/finance/earnings.py
python_upwork_oauth2-3.2.0.dist-info/LICENSE
python_upwork_oauth2-3.2.0.dist-info/METADATA
python_upwork_oauth2-3.2.0.dist-info/WHEEL
python_upwork_oauth2-3.2.0.dist-info/top_level.txt
python_upwork_oauth2-3.2.0.dist-info/RECORD
