Metadata-Version: 2.1
Name: python-upwork-oauth2
Version: 3.2.0
Summary: Python bindings for Upwork API (OAuth2)
Home-page: https://github.com/upwork/python-upwork-oauth2
Author: Maksym Novozhylov
Author-email: mnovozhilov@upwork.com
License: Apache Software License 2.0
Keywords: python-upwork-oauth2
Classifier: Development Status :: 5 - Production/Stable
Classifier: Environment :: Web Environment
Classifier: Intended Audience :: Developers
Classifier: License :: OSI Approved :: Apache Software License
Classifier: Natural Language :: English
Classifier: Operating System :: OS Independent
Classifier: Programming Language :: Python :: 3
Classifier: Topic :: Software Development :: Libraries :: Python Modules
Classifier: Topic :: Utilities
Requires-Python: >=3.8
License-File: LICENSE
Requires-Dist: requests_oauthlib==1.3.1
